LoRaPi5/__init__.py
LoRaPi5/constants.py
LoRaPi5/lora.py
lorapi5-0.0.3.dist-info/licenses/LICENSE
lorapi5-0.0.3.dist-info/METADATA
lorapi5-0.0.3.dist-info/WHEEL
lorapi5-0.0.3.dist-info/top_level.txt
lorapi5-0.0.3.dist-info/RECORD
