Metadata-Version: 2.4
Name: LoRaPi5
Version: 0.0.3
Summary: A simple LoRa API for the raspberryPi5
Author-email: goldenmatrix <goldenmatrix@gmail.com>
License-Expression: MIT
Project-URL: Homepage, https://github.com/leonardonels/LoRaPi5
Project-URL: Issues, https://github.com/leonardonels/LoRaPi5/issues
Classifier: Programming Language :: Python :: 3
Classifier: Operating System :: OS Independent
Requires-Python: >=3.9
License-File: LICENSE
Requires-Dist: gpiozero>=2.0.1
Requires-Dist: spidev>=3.5
Dynamic: license-file
